odoo/addons/purchase_vendor_promotion/README.rst
odoo/addons/purchase_vendor_promotion/__init__.py
odoo/addons/purchase_vendor_promotion/__manifest__.py
odoo/addons/purchase_vendor_promotion/i18n/fr.po
odoo/addons/purchase_vendor_promotion/i18n/it.po
odoo/addons/purchase_vendor_promotion/i18n/purchase_vendor_promotion.pot
odoo/addons/purchase_vendor_promotion/models/__init__.py
odoo/addons/purchase_vendor_promotion/models/product_supplierinfo.py
odoo/addons/purchase_vendor_promotion/models/purchase_order_line.py
odoo/addons/purchase_vendor_promotion/models/stock_warehouse_orderpoint.py
odoo/addons/purchase_vendor_promotion/readme/CONTRIBUTORS.rst
odoo/addons/purchase_vendor_promotion/readme/DESCRIPTION.rst
odoo/addons/purchase_vendor_promotion/static/description/icon.png
odoo/addons/purchase_vendor_promotion/static/description/index.html
odoo/addons/purchase_vendor_promotion/tests/__init__.py
odoo/addons/purchase_vendor_promotion/tests/test_vendor_promotion.py
odoo/addons/purchase_vendor_promotion/views/product_views.xml
odoo/addons/purchase_vendor_promotion/views/purchase_order_views.xml
odoo/addons/purchase_vendor_promotion/views/stock_orderpoint_views.xml
odoo_addon_purchase_vendor_promotion-16.0.1.0.1.dist-info/METADATA
odoo_addon_purchase_vendor_promotion-16.0.1.0.1.dist-info/WHEEL
odoo_addon_purchase_vendor_promotion-16.0.1.0.1.dist-info/top_level.txt
odoo_addon_purchase_vendor_promotion-16.0.1.0.1.dist-info/RECORD
