Metadata-Version: 2.1
Name: odoo-addon-purchase_vendor_promotion
Version: 16.0.1.0.1
Summary: Purchase Vendor Promotion
Home-page: https://github.com/OCA/purchase-workflow
Author: Camptocamp, Odoo Community Association (OCA)
Author-email: support@odoo-community.org
License: AGPL-3
Classifier: Programming Language :: Python
Classifier: Framework :: Odoo
Classifier: Framework :: Odoo :: 16.0
Classifier: License :: OSI Approved :: GNU Affero General Public License v3
Classifier: Development Status :: 4 - Beta
Requires-Python: >=3.10
Requires-Dist: odoo<16.1dev,>=16.0a
